cubrium/__about__.py
cubrium/__init__.py
cubrium/assembly.py
cubrium/constitution.py
cubrium/helpers.py
cubrium/kinematics.py
cubrium/kinetics.py
cubrium/loadcase.py
cubrium/solver.py
cubrium/system.py
cubrium/writer.py
cubrium-0.1.5.dist-info/LICENSE
cubrium-0.1.5.dist-info/METADATA
cubrium-0.1.5.dist-info/WHEEL
cubrium-0.1.5.dist-info/top_level.txt
cubrium-0.1.5.dist-info/RECORD
